funniestnima/__init__.py
funniestnima-0.2.dist-info/METADATA
funniestnima-0.2.dist-info/WHEEL
funniestnima-0.2.dist-info/top_level.txt
funniestnima-0.2.dist-info/RECORD
