Metadata-Version: 2.1
Name: funniestnima
Version: 0.2
Summary: The funniest joke in the world
Home-page: http://github.com/iw4p/funniestnima
Author: Flying Circus
Author-email: flyingcircus@example.com
License: MIT
Platform: UNKNOWN
